django_model_to_dict/__init__.py
django_model_to_dict/apps.py
django_model_to_dict/mixins.py
django_model_to_dict/models.py
django_model_to_dict/settings.py
django_model_to_dict/plugins/__init__.py
django_model_to_dict/plugins/serialization/__init__.py
django_model_to_dict/plugins/serialization/filebrowser_field.py
django_model_to_dict-0.2.1.dist-info/DESCRIPTION.rst
django_model_to_dict-0.2.1.dist-info/METADATA
django_model_to_dict-0.2.1.dist-info/RECORD
django_model_to_dict-0.2.1.dist-info/WHEEL
django_model_to_dict-0.2.1.dist-info/metadata.json
django_model_to_dict-0.2.1.dist-info/top_level.txt
