Metadata-Version: 2.0
Name: django-model-to-dict
Version: 0.2.1
Summary: Django Model to Python dict serialization mixin.
Home-page: https://github.com/gbezyuk/django-model-to-dict
Author: Grigoriy Beziuk
Author-email: me@gbezyuk.ru
License: MIT
Keywords: django-model-to-dict
Platform: UNKNOWN
Classifier: Development Status :: 3 - Alpha
Classifier: Framework :: Django
Classifier: Framework :: Django :: 1.10
Classifier: Intended Audience :: Developers
Classifier: License :: OSI Approved :: BSD License
Classifier: Natural Language :: English
Classifier: Programming Language :: Python :: 2
Classifier: Programming Language :: Python :: 2.7
Classifier: Programming Language :: Python :: 3
Classifier: Programming Language :: Python :: 3.4
Classifier: Programming Language :: Python :: 3.5
